[
    {
        "latLng": {"lat": 33.614769, "lng": -112.112512},
        "title": "Rhonda Lake LPC - AZCrossPoint",
        "specialties": ["Trauma/PTSD", "EMDR Therapy"],
        "phone": "623-451-7328",
        "email": "rhonda@AZcrosspoint.com",
        "addressLine": null,
        "city": null,
        "state": null,
        "zip": null,
        "website": "www.azcrosspoint.com"
    },
    {
        "latLng": {"lat": 33.614769, "lng": -112.112512},
        "title": "Wholeness 2 Peace Care Services",
        "specialties": ["Children", "Adolescents", "Marriage", "Anxiety"],
        "phone": "623-688-1537",
        "email": "office@wholeness2peace.com",
        "addressLine": "10000 North 31st Ave. Suite A105",
        "city": "Phoenix",
        "state": "Az",
        "zip": "85051",
        "website": "www.wholeness2peacecareservices.com"
    },
    {
        "latLng": {"lat": 33.614769, "lng": -112.112512},
        "title": "Taking Root Counseling",
        "specialties": ["Children", "Adolescents", "Trauma/PTSD", "EMDR Therapy", "Depression", "Grief"],
        "phone": "602-908-0805",
        "email": null,
        "addressLine": null,
        "city": null,
        "state": null,
        "zip": null,
        "website": "www.takingrootcounseling.com"
    },
    {
        "latLng": {"lat": 33.614769, "lng": -112.112512},
        "title": "Northwest Christian Counseling LLC",
        "specialties": ["Marriage", "Adolescents", "Trauma/PTSD", "Sexual Addictions", "Depression", "Grief"],
        "phone": "623-680-8172",
        "email": "nwccllc@yahoo.com",
        "addressLine": null,
        "city": null,
        "state": null,
        "zip": null,
        "website": "www.nwchristiancounseling.com"
    },
    {
        "latLng": {"lat": 33.614769, "lng": -112.112512},
        "title": "Mike Sweeney LCSW",
        "specialties": null,
        "phone": "623-334-9700",
        "email": null,
        "addressLine": null,
        "city": null,
        "state": null,
        "zip": null,
        "website": null
    },
    {
        "latLng": {"lat": 33.614769, "lng": -112.112512},
        "title": "Sandra O'Connell",
        "specialties": ["Trauma/PTSD", "Spirituality", "Life Transitions"],
        "phone": "602-428-9445",
        "email": null,
        "addressLine": null,
        "city": null,
        "state": null,
        "zip": null,
        "website": "https://www.psychologytoday.com/us/therapists/sandra-oconnell-phoenix-az/229219"
    },
    {
        "latLng": {"lat": 33.614769, "lng": -112.112512},
        "title": "Thrive Therapy - Phoenix",
        "specialties": ["Marriage/Couples", "Children/Adolescents", "Trauma/PTSD", "Anxiety", "Depression", "Eating Disorders", "OCD"],
        "phone": "602-529-6557",
        "email": null,
        "addressLine": null,
        "city": null,
        "state": null,
        "zip": null,
        "website": "Thrivetherapyphx.com"
    },
    {
        "latLng": {"lat": 33.614769, "lng": -112.112512},
        "title": "Thrive Therapy - Scottsdale",
        "specialties": ["Marriage/Couples", "Children/Adolescents", "Trauma/PTSD", "Anxiety", "Depression", "Eating Disorders", "OCD"],
        "phone": "480-508-1144",
        "email": null,
        "addressLine": null,
        "city": null,
        "state": null,
        "zip": null,
        "website": "Thrivetherapyphx.com"
    },
    {
        "latLng": {"lat": 33.614769, "lng": -112.112512},
        "title": "Alliance Group",
        "specialties": ["Marriage/Couples", "Children/Adolescents", "Trauma/PTSD", "Anxiety", "Depression", "Eating Disorders", "Attachment Disorders", "Family Counseling", "Addiction"],
        "phone": "602-610-8250",
        "email": null,
        "addressLine": null,
        "city": null,
        "state": null,
        "zip": null,
        "website": "https://allianceccgroup.com/"
    },
    {
        "latLng": {"lat": 33.614769, "lng": -112.112512},
        "title": "Grand Canyon Counseling Services",
        "specialties": ["Addiction", "Depression", "Anxiety", "Marriage/Couples", "Family Counseling", "Grief"],
        "phone": "602-942-2787",
        "email": null,
        "addressLine": null,
        "city": null,
        "state": null,
        "zip": null,
        "website": "www.grandcanyoncounseling.com"
    },
    {
        "latLng": {"lat": 33.614769, "lng": -112.112512},
        "title": "Agape Christian Counseling",
        "specialties": ["Marriage/Couples", "Family Counseling", "Children/Adolescents", "Anxiety/Depression", "Addiction", "Trauma/PTSD", "Self Esteem", "OCD"],
        "phone": "623-842-3696",
        "email": null,
        "addressLine": null,
        "city": null,
        "state": null,
        "zip": null,
        "website": "www.agapechristiancounseling.org"
    },
    {
        "latLng": {"lat": 33.614769, "lng": -112.112512},
        "title": "Compassion Christian Counseling Services ",
        "specialties": ["Eating Disorders"],
        "phone": "623-935-9767",
        "email": "CompassionChristianCounseling@msn.com",
        "addressLine": "13657 W. McDowell Rd Suite 209",
        "city": "Goodyear",
        "state": "Az",
        "zip": "85395",
        "website": null
    },
    {
        "latLng": {"lat": 33.614769, "lng": -112.112512},
        "title": "Christian Counseling Center of Scottsdale",
        "specialties": ["Anxiety/Depression", "Eating Disorders", "Children/Adolescents", "Marriage/Couples", "Addiction", "Stress", "Grief"],
        "phone": "480-922-5696",
        "email": "larcychris@christiancounselingscottsdale.com",
        "addressLine": null,
        "city": null,
        "state": null,
        "zip": null,
        "website": "www.christiancounselingscottsdale.com"
    },
    {
        "latLng": {"lat": 33.614769, "lng": -112.112512},
        "title": "Connections Christian Counseling, LLC",
        "specialties": null,
        "phone": "623-297-4756",
        "email": "lena@lenawright.com",
        "addressLine": "12211 W. Bell Road #205",
        "city": "Surprise",
        "state": "Az",
        "zip": "85374",
        "website": null
    },
    {
        "latLng": {"lat": 33.614769, "lng": -112.112512},
        "title": "Doorways Counseling",
        "specialties": ["Children/Adolescents", "Eating Disorders", "Anxiety/Depression", "Addiction"],
        "phone": "602-960-2051",
        "email": null,
        "addressLine": "1825 E. Northern Ave. Suite 200",
        "city": "Phoenix",
        "state": "Az",
        "zip": "85020",
        "website": "www.doorwaysarizona.com"
    },
    {
        "latLng": {"lat": 33.614769, "lng": -112.112512},
        "title": "Theresa Buot-Smith",
        "specialties": null,
        "phone": "602-494-7110",
        "email": null,
        "addressLine": "4545 E. Shea, #112",
        "city": "Phoenix",
        "state": "Az",
        "zip": "85028",
        "website": null
    },
    {
        "latLng": {"lat": 33.614769, "lng": -112.112512},
        "title": "Marie Gronley",
        "specialties": null,
        "phone": null,
        "email": null,
        "addressLine": "15849 N. 71st Street, Suite 100, Scottsdale, AZ",
        "city": "Scottsdale",
        "state": "Az",
        "zip": "85254",
        "website": null
    }
]